{
  "id": 3341246873,
  "name": "Docker",
  "node_id": "WFR_kwLOAlosUs7HJ2GZ",
  "head_branch": "master",
  "head_sha": "102909e00404cd25a62dbd5142790a8e69f1a681",
  "path": ".github/workflows/docker.yml",
  "display_title": "fix: small bump to shillelagh (#21953)",
  "run_number": 26423,
  "event": "push",
  "status": "completed",
  "conclusion": "success",
  "workflow_id": 3465823,
  "check_suite_id": 9002546407,
  "check_suite_node_id": "CS_kwDOAlosUs8AAAACGJf05w",
  "url": "https://api.github.com/repos/apache/superset/actions/runs/3341246873",
  "created_at": "2022-10-27T22:08:56Z",
  "updated_at": "2022-10-27T22:58:27Z",
  "actor": {
    "login": "AAfghahi",
    "id": 48933336,
    "node_id": "MDQ6VXNlcjQ4OTMzMzM2",
    "avatar_url": "https://avatars.githubusercontent.com/u/48933336?v=4",
    "gravatar_id": "",
    "url": "https://api.github.com/users/AAfghahi",
    "html_url": "https://github.com/AAfghahi",
    "followers_url": "https://api.github.com/users/AAfghahi/followers",
    "following_url": "https://api.github.com/users/AAfghahi/following{/other_user}",
    "gists_url": "https://api.github.com/users/AAfghahi/gists{/gist_id}",
    "starred_url": "https://api.github.com/users/AAfghahi/starred{/owner}{/repo}",
    "subscriptions_url": "https://api.github.com/users/AAfghahi/subscriptions",
    "organizations_url": "https://api.github.com/users/AAfghahi/orgs",
    "repos_url": "https://api.github.com/users/AAfghahi/repos",
    "events_url": "https://api.github.com/users/AAfghahi/events{/privacy}",
    "received_events_url": "https://api.github.com/users/AAfghahi/received_events",
    "type": "User",
    "site_admin": false
  },
  "run_attempt": 1,
  "referenced_workflows": [],
  "run_started_at": "2022-10-27T22:08:56Z",
  "triggering_actor": {
    "login": "AAfghahi",
    "id": 48933336,
    "node_id": "MDQ6VXNlcjQ4OTMzMzM2",
    "avatar_url": "https://avatars.githubusercontent.com/u/48933336?v=4",
    "gravatar_id": "",
    "url": "https://api.github.com/users/AAfghahi",
    "html_url": "https://github.com/AAfghahi",
    "followers_url": "https://api.github.com/users/AAfghahi/followers",
    "following_url": "https://api.github.com/users/AAfghahi/following{/other_user}",
    "gists_url": "https://api.github.com/users/AAfghahi/gists{/gist_id}",
    "starred_url": "https://api.github.com/users/AAfghahi/starred{/owner}{/repo}",
    "subscriptions_url": "https://api.github.com/users/AAfghahi/subscriptions",
    "organizations_url": "https://api.github.com/users/AAfghahi/orgs",
    "repos_url": "https://api.github.com/users/AAfghahi/repos",
    "events_url": "https://api.github.com/users/AAfghahi/events{/privacy}",
    "received_events_url": "https://api.github.com/users/AAfghahi/received_events",
    "type": "User",
    "site_admin": false
  },
  "jobs_url": "https://api.github.com/repos/apache/superset/actions/runs/3341246873/jobs",
  "logs_url": "https://api.github.com/repos/apache/superset/actions/runs/3341246873/logs",
  "check_suite_url": "https://api.github.com/repos/apache/superset/check-suites/9002546407",
  "artifacts_url": "https://api.github.com/repos/apache/superset/actions/runs/3341246873/artifacts",
  "cancel_url": "https://api.github.com/repos/apache/superset/actions/runs/3341246873/cancel",
  "rerun_url": "https://api.github.com/repos/apache/superset/actions/runs/3341246873/rerun",
  "previous_attempt_url": null,
  "workflow_url": "https://api.github.com/repos/apache/superset/actions/workflows/3465823",
  "head_commit": {
    "id": "102909e00404cd25a62dbd5142790a8e69f1a681",
    "tree_id": "88a74b0ae5002a9de30f9d34b3eb3f36a36967ea",
    "message": "fix: small bump to shillelagh (#21953)",
    "timestamp": "2022-10-27T22:08:51Z",
    "author": {
      "name": "AAfghahi",
      "email": "48933336+AAfghahi@users.noreply.github.com"
    },
    "committer": {
      "name": "GitHub",
      "email": "noreply@github.com"
    }
  }
}
