{
  "id": 1930233804,
  "name": "Docker",
  "node_id": "WFR_kwLOAlosUs5zDQfM",
  "head_branch": "master",
  "head_sha": "6fe24316765af2e5e004c2daa2ef075e899e235a",
  "run_number": 18112,
  "event": "push",
  "status": "completed",
  "conclusion": "success",
  "workflow_id": 3465823,
  "check_suite_id": 5526833129,
  "check_suite_node_id": "CS_kwDOAlosUs8AAAABSWzH6Q",
  "url": "https://api.github.com/repos/apache/superset/actions/runs/1930233804",
  "created_at": "2022-03-03T20:22:55Z",
  "updated_at": "2022-03-03T20:37:34Z",
  "actor": {
    "login": "rusackas",
    "id": 812905,
    "node_id": "MDQ6VXNlcjgxMjkwNQ==",
    "avatar_url": "https://avatars.githubusercontent.com/u/812905?v=4",
    "gravatar_id": "",
    "url": "https://api.github.com/users/rusackas",
    "html_url": "https://github.com/rusackas",
    "followers_url": "https://api.github.com/users/rusackas/followers",
    "following_url": "https://api.github.com/users/rusackas/following{/other_user}",
    "gists_url": "https://api.github.com/users/rusackas/gists{/gist_id}",
    "starred_url": "https://api.github.com/users/rusackas/starred{/owner}{/repo}",
    "subscriptions_url": "https://api.github.com/users/rusackas/subscriptions",
    "organizations_url": "https://api.github.com/users/rusackas/orgs",
    "repos_url": "https://api.github.com/users/rusackas/repos",
    "events_url": "https://api.github.com/users/rusackas/events{/privacy}",
    "received_events_url": "https://api.github.com/users/rusackas/received_events",
    "type": "User",
    "site_admin": false
  },
  "run_attempt": 1,
  "run_started_at": "2022-03-03T20:22:55Z",
  "jobs_url": "https://api.github.com/repos/apache/superset/actions/runs/1930233804/jobs",
  "logs_url": "https://api.github.com/repos/apache/superset/actions/runs/1930233804/logs",
  "check_suite_url": "https://api.github.com/repos/apache/superset/check-suites/5526833129",
  "artifacts_url": "https://api.github.com/repos/apache/superset/actions/runs/1930233804/artifacts",
  "cancel_url": "https://api.github.com/repos/apache/superset/actions/runs/1930233804/cancel",
  "rerun_url": "https://api.github.com/repos/apache/superset/actions/runs/1930233804/rerun",
  "previous_attempt_url": null,
  "workflow_url": "https://api.github.com/repos/apache/superset/actions/workflows/3465823",
  "head_commit": {
    "id": "6fe24316765af2e5e004c2daa2ef075e899e235a",
    "tree_id": "ee8bf5a04993f77bc2a84eb47ceb2abec578fcd0",
    "message": "fix(nested-tab-available): make the another tabs into one tabs available (#18877)\n\n* fix(nested-tab-available): make the another tabs into one tabs available\r\n\r\n* fix(netsted-tab): remove code of disable nested tab",
    "timestamp": "2022-03-03T20:22:49Z",
    "author": {
      "name": "smileydev",
      "email": "47900232+prosdev0107@users.noreply.github.com"
    },
    "committer": {
      "name": "GitHub",
      "email": "noreply@github.com"
    }
  }
}
