{
  "id": 3709332072,
  "name": "Docker",
  "node_id": "WFR_kwLOAlosUs7dF-po",
  "head_branch": "master",
  "head_sha": "bdeedaaf80deb5785d82b786e713c8a3cb579ee3",
  "path": ".github/workflows/docker.yml",
  "display_title": "chore: set Snowflake user agent (#22432)",
  "run_number": 27980,
  "event": "push",
  "status": "completed",
  "conclusion": "success",
  "workflow_id": 3465823,
  "check_suite_id": 9899564939,
  "check_suite_node_id": "CS_kwDOAlosUs8AAAACTg9fiw",
  "url": "https://api.github.com/repos/apache/superset/actions/runs/3709332072",
  "created_at": "2022-12-16T01:08:43Z",
  "updated_at": "2022-12-16T01:23:07Z",
  "actor": {
    "login": "betodealmeida",
    "id": 1534870,
    "node_id": "MDQ6VXNlcjE1MzQ4NzA=",
    "avatar_url": "https://avatars.githubusercontent.com/u/1534870?v=4",
    "gravatar_id": "",
    "url": "https://api.github.com/users/betodealmeida",
    "html_url": "https://github.com/betodealmeida",
    "followers_url": "https://api.github.com/users/betodealmeida/followers",
    "following_url": "https://api.github.com/users/betodealmeida/following{/other_user}",
    "gists_url": "https://api.github.com/users/betodealmeida/gists{/gist_id}",
    "starred_url": "https://api.github.com/users/betodealmeida/starred{/owner}{/repo}",
    "subscriptions_url": "https://api.github.com/users/betodealmeida/subscriptions",
    "organizations_url": "https://api.github.com/users/betodealmeida/orgs",
    "repos_url": "https://api.github.com/users/betodealmeida/repos",
    "events_url": "https://api.github.com/users/betodealmeida/events{/privacy}",
    "received_events_url": "https://api.github.com/users/betodealmeida/received_events",
    "type": "User",
    "site_admin": false
  },
  "run_attempt": 1,
  "referenced_workflows": [],
  "run_started_at": "2022-12-16T01:08:43Z",
  "triggering_actor": {
    "login": "betodealmeida",
    "id": 1534870,
    "node_id": "MDQ6VXNlcjE1MzQ4NzA=",
    "avatar_url": "https://avatars.githubusercontent.com/u/1534870?v=4",
    "gravatar_id": "",
    "url": "https://api.github.com/users/betodealmeida",
    "html_url": "https://github.com/betodealmeida",
    "followers_url": "https://api.github.com/users/betodealmeida/followers",
    "following_url": "https://api.github.com/users/betodealmeida/following{/other_user}",
    "gists_url": "https://api.github.com/users/betodealmeida/gists{/gist_id}",
    "starred_url": "https://api.github.com/users/betodealmeida/starred{/owner}{/repo}",
    "subscriptions_url": "https://api.github.com/users/betodealmeida/subscriptions",
    "organizations_url": "https://api.github.com/users/betodealmeida/orgs",
    "repos_url": "https://api.github.com/users/betodealmeida/repos",
    "events_url": "https://api.github.com/users/betodealmeida/events{/privacy}",
    "received_events_url": "https://api.github.com/users/betodealmeida/received_events",
    "type": "User",
    "site_admin": false
  },
  "jobs_url": "https://api.github.com/repos/apache/superset/actions/runs/3709332072/jobs",
  "logs_url": "https://api.github.com/repos/apache/superset/actions/runs/3709332072/logs",
  "check_suite_url": "https://api.github.com/repos/apache/superset/check-suites/9899564939",
  "artifacts_url": "https://api.github.com/repos/apache/superset/actions/runs/3709332072/artifacts",
  "cancel_url": "https://api.github.com/repos/apache/superset/actions/runs/3709332072/cancel",
  "rerun_url": "https://api.github.com/repos/apache/superset/actions/runs/3709332072/rerun",
  "previous_attempt_url": null,
  "workflow_url": "https://api.github.com/repos/apache/superset/actions/workflows/3465823",
  "head_commit": {
    "id": "bdeedaaf80deb5785d82b786e713c8a3cb579ee3",
    "tree_id": "10f5c60d2dc0039909c51f17671d7ba4d730a669",
    "message": "chore: set Snowflake user agent (#22432)",
    "timestamp": "2022-12-16T01:08:34Z",
    "author": {
      "name": "Beto Dealmeida",
      "email": "roberto@dealmeida.net"
    },
    "committer": {
      "name": "GitHub",
      "email": "noreply@github.com"
    }
  }
}
