{
  "id": 2996975390,
  "name": "Docker",
  "node_id": "WFR_kwLOAlosUs6yojce",
  "head_branch": "master",
  "head_sha": "f07cd2d1eef2a7309f1a18cbffe1ea03544b5b8c",
  "path": ".github/workflows/docker.yml",
  "run_number": 24792,
  "event": "pull_request",
  "status": "completed",
  "conclusion": "action_required",
  "workflow_id": 3465823,
  "check_suite_id": 8146538241,
  "check_suite_node_id": "CS_kwDOAlosUs8AAAAB5ZJPAQ",
  "url": "https://api.github.com/repos/apache/superset/actions/runs/2996975390",
  "created_at": "2022-09-06T01:36:42Z",
  "updated_at": "2022-09-06T01:36:42Z",
  "actor": {
    "login": "xiayanzheng",
    "id": 14834951,
    "node_id": "MDQ6VXNlcjE0ODM0OTUx",
    "avatar_url": "https://avatars.githubusercontent.com/u/14834951?v=4",
    "gravatar_id": "",
    "url": "https://api.github.com/users/xiayanzheng",
    "html_url": "https://github.com/xiayanzheng",
    "followers_url": "https://api.github.com/users/xiayanzheng/followers",
    "following_url": "https://api.github.com/users/xiayanzheng/following{/other_user}",
    "gists_url": "https://api.github.com/users/xiayanzheng/gists{/gist_id}",
    "starred_url": "https://api.github.com/users/xiayanzheng/starred{/owner}{/repo}",
    "subscriptions_url": "https://api.github.com/users/xiayanzheng/subscriptions",
    "organizations_url": "https://api.github.com/users/xiayanzheng/orgs",
    "repos_url": "https://api.github.com/users/xiayanzheng/repos",
    "events_url": "https://api.github.com/users/xiayanzheng/events{/privacy}",
    "received_events_url": "https://api.github.com/users/xiayanzheng/received_events",
    "type": "User",
    "site_admin": false
  },
  "run_attempt": 1,
  "referenced_workflows": [],
  "run_started_at": "2022-09-06T01:36:42Z",
  "triggering_actor": {
    "login": "xiayanzheng",
    "id": 14834951,
    "node_id": "MDQ6VXNlcjE0ODM0OTUx",
    "avatar_url": "https://avatars.githubusercontent.com/u/14834951?v=4",
    "gravatar_id": "",
    "url": "https://api.github.com/users/xiayanzheng",
    "html_url": "https://github.com/xiayanzheng",
    "followers_url": "https://api.github.com/users/xiayanzheng/followers",
    "following_url": "https://api.github.com/users/xiayanzheng/following{/other_user}",
    "gists_url": "https://api.github.com/users/xiayanzheng/gists{/gist_id}",
    "starred_url": "https://api.github.com/users/xiayanzheng/starred{/owner}{/repo}",
    "subscriptions_url": "https://api.github.com/users/xiayanzheng/subscriptions",
    "organizations_url": "https://api.github.com/users/xiayanzheng/orgs",
    "repos_url": "https://api.github.com/users/xiayanzheng/repos",
    "events_url": "https://api.github.com/users/xiayanzheng/events{/privacy}",
    "received_events_url": "https://api.github.com/users/xiayanzheng/received_events",
    "type": "User",
    "site_admin": false
  },
  "jobs_url": "https://api.github.com/repos/apache/superset/actions/runs/2996975390/jobs",
  "logs_url": "https://api.github.com/repos/apache/superset/actions/runs/2996975390/logs",
  "check_suite_url": "https://api.github.com/repos/apache/superset/check-suites/8146538241",
  "artifacts_url": "https://api.github.com/repos/apache/superset/actions/runs/2996975390/artifacts",
  "cancel_url": "https://api.github.com/repos/apache/superset/actions/runs/2996975390/cancel",
  "rerun_url": "https://api.github.com/repos/apache/superset/actions/runs/2996975390/rerun",
  "previous_attempt_url": null,
  "workflow_url": "https://api.github.com/repos/apache/superset/actions/workflows/3465823",
  "head_commit": {
    "id": "f07cd2d1eef2a7309f1a18cbffe1ea03544b5b8c",
    "tree_id": "adacb88a01205c13c1f8f0bb560c3e1436718137",
    "message": "Merge branch 'apache:master' into master",
    "timestamp": "2022-09-06T01:36:35Z",
    "author": {
      "name": "LF",
      "email": "xiayanzheng@outlook.com"
    },
    "committer": {
      "name": "GitHub",
      "email": "noreply@github.com"
    }
  }
}
