{
  "id": 9892567769,
  "name": "Build & publish docker images",
  "node_id": "WFR_kwLOAlosUs8AAAACTaSa2Q",
  "head_branch": "master",
  "head_sha": "2336e9e9b3938fb5a5ae74bbd70344b2a727bd98",
  "path": ".github/workflows/docker.yml",
  "display_title": "docs: Added Keycloak auth configuration",
  "run_number": 45353,
  "event": "pull_request",
  "status": "completed",
  "conclusion": "action_required",
  "workflow_id": 3465823,
  "check_suite_id": 25894768183,
  "check_suite_node_id": "CS_kwDOAlosUs8AAAAGB3LONw",
  "url": "https://api.github.com/repos/apache/superset/actions/runs/9892567769",
  "created_at": "2024-07-11T13:42:04Z",
  "updated_at": "2024-07-11T13:42:04Z",
  "actor": {
    "login": "lindner-tj",
    "id": 171801281,
    "node_id": "U_kgDOCj16wQ",
    "avatar_url": "https://avatars.githubusercontent.com/u/171801281?v=4",
    "gravatar_id": "",
    "url": "https://api.github.com/users/lindner-tj",
    "html_url": "https://github.com/lindner-tj",
    "followers_url": "https://api.github.com/users/lindner-tj/followers",
    "following_url": "https://api.github.com/users/lindner-tj/following{/other_user}",
    "gists_url": "https://api.github.com/users/lindner-tj/gists{/gist_id}",
    "starred_url": "https://api.github.com/users/lindner-tj/starred{/owner}{/repo}",
    "subscriptions_url": "https://api.github.com/users/lindner-tj/subscriptions",
    "organizations_url": "https://api.github.com/users/lindner-tj/orgs",
    "repos_url": "https://api.github.com/users/lindner-tj/repos",
    "events_url": "https://api.github.com/users/lindner-tj/events{/privacy}",
    "received_events_url": "https://api.github.com/users/lindner-tj/received_events",
    "type": "User",
    "site_admin": false
  },
  "run_attempt": 1,
  "referenced_workflows": [],
  "run_started_at": "2024-07-11T13:42:04Z",
  "triggering_actor": {
    "login": "lindner-tj",
    "id": 171801281,
    "node_id": "U_kgDOCj16wQ",
    "avatar_url": "https://avatars.githubusercontent.com/u/171801281?v=4",
    "gravatar_id": "",
    "url": "https://api.github.com/users/lindner-tj",
    "html_url": "https://github.com/lindner-tj",
    "followers_url": "https://api.github.com/users/lindner-tj/followers",
    "following_url": "https://api.github.com/users/lindner-tj/following{/other_user}",
    "gists_url": "https://api.github.com/users/lindner-tj/gists{/gist_id}",
    "starred_url": "https://api.github.com/users/lindner-tj/starred{/owner}{/repo}",
    "subscriptions_url": "https://api.github.com/users/lindner-tj/subscriptions",
    "organizations_url": "https://api.github.com/users/lindner-tj/orgs",
    "repos_url": "https://api.github.com/users/lindner-tj/repos",
    "events_url": "https://api.github.com/users/lindner-tj/events{/privacy}",
    "received_events_url": "https://api.github.com/users/lindner-tj/received_events",
    "type": "User",
    "site_admin": false
  },
  "jobs_url": "https://api.github.com/repos/apache/superset/actions/runs/9892567769/jobs",
  "logs_url": "https://api.github.com/repos/apache/superset/actions/runs/9892567769/logs",
  "check_suite_url": "https://api.github.com/repos/apache/superset/check-suites/25894768183",
  "artifacts_url": "https://api.github.com/repos/apache/superset/actions/runs/9892567769/artifacts",
  "cancel_url": "https://api.github.com/repos/apache/superset/actions/runs/9892567769/cancel",
  "rerun_url": "https://api.github.com/repos/apache/superset/actions/runs/9892567769/rerun",
  "previous_attempt_url": null,
  "workflow_url": "https://api.github.com/repos/apache/superset/actions/workflows/3465823",
  "head_commit": {
    "id": "2336e9e9b3938fb5a5ae74bbd70344b2a727bd98",
    "tree_id": "10dc55f73b8c447b84a8a85f8c9083b5a2a5548a",
    "message": "Added mention of Flask-OpenID as required dependency\n\nAnswering the question of @kormpakis made me aware that I forgot to include this.",
    "timestamp": "2024-07-11T13:41:59Z",
    "author": {
      "name": "lindner-tj",
      "email": "thomas.jonas@lindner-group.com"
    },
    "committer": {
      "name": "GitHub",
      "email": "noreply@github.com"
    }
  }
}
