{
  "id": 6075435197,
  "name": "Docker",
  "node_id": "WFR_kwLOAlosUs8AAAABah_IvQ",
  "head_branch": "master",
  "head_sha": "6d5949d4840893c47f8c61bc6e71961221af051f",
  "path": ".github/workflows/docker.yml",
  "display_title": "docs(databases): add Atgenomix SeqsLab as the supported database along with db engine spec",
  "run_number": 35451,
  "event": "pull_request",
  "status": "completed",
  "conclusion": "action_required",
  "workflow_id": 3465823,
  "check_suite_id": 15808083035,
  "check_suite_node_id": "CS_kwDOAlosUs8AAAADrjw0Ww",
  "url": "https://api.github.com/repos/apache/superset/actions/runs/6075435197",
  "created_at": "2023-09-04T15:37:55Z",
  "updated_at": "2023-09-04T15:37:55Z",
  "actor": {
    "login": "allen-chang",
    "id": 13267303,
    "node_id": "MDQ6VXNlcjEzMjY3MzAz",
    "avatar_url": "https://avatars.githubusercontent.com/u/13267303?v=4",
    "gravatar_id": "",
    "url": "https://api.github.com/users/allen-chang",
    "html_url": "https://github.com/allen-chang",
    "followers_url": "https://api.github.com/users/allen-chang/followers",
    "following_url": "https://api.github.com/users/allen-chang/following{/other_user}",
    "gists_url": "https://api.github.com/users/allen-chang/gists{/gist_id}",
    "starred_url": "https://api.github.com/users/allen-chang/starred{/owner}{/repo}",
    "subscriptions_url": "https://api.github.com/users/allen-chang/subscriptions",
    "organizations_url": "https://api.github.com/users/allen-chang/orgs",
    "repos_url": "https://api.github.com/users/allen-chang/repos",
    "events_url": "https://api.github.com/users/allen-chang/events{/privacy}",
    "received_events_url": "https://api.github.com/users/allen-chang/received_events",
    "type": "User",
    "site_admin": false
  },
  "run_attempt": 1,
  "referenced_workflows": [],
  "run_started_at": "2023-09-04T15:37:55Z",
  "triggering_actor": {
    "login": "allen-chang",
    "id": 13267303,
    "node_id": "MDQ6VXNlcjEzMjY3MzAz",
    "avatar_url": "https://avatars.githubusercontent.com/u/13267303?v=4",
    "gravatar_id": "",
    "url": "https://api.github.com/users/allen-chang",
    "html_url": "https://github.com/allen-chang",
    "followers_url": "https://api.github.com/users/allen-chang/followers",
    "following_url": "https://api.github.com/users/allen-chang/following{/other_user}",
    "gists_url": "https://api.github.com/users/allen-chang/gists{/gist_id}",
    "starred_url": "https://api.github.com/users/allen-chang/starred{/owner}{/repo}",
    "subscriptions_url": "https://api.github.com/users/allen-chang/subscriptions",
    "organizations_url": "https://api.github.com/users/allen-chang/orgs",
    "repos_url": "https://api.github.com/users/allen-chang/repos",
    "events_url": "https://api.github.com/users/allen-chang/events{/privacy}",
    "received_events_url": "https://api.github.com/users/allen-chang/received_events",
    "type": "User",
    "site_admin": false
  },
  "jobs_url": "https://api.github.com/repos/apache/superset/actions/runs/6075435197/jobs",
  "logs_url": "https://api.github.com/repos/apache/superset/actions/runs/6075435197/logs",
  "check_suite_url": "https://api.github.com/repos/apache/superset/check-suites/15808083035",
  "artifacts_url": "https://api.github.com/repos/apache/superset/actions/runs/6075435197/artifacts",
  "cancel_url": "https://api.github.com/repos/apache/superset/actions/runs/6075435197/cancel",
  "rerun_url": "https://api.github.com/repos/apache/superset/actions/runs/6075435197/rerun",
  "previous_attempt_url": null,
  "workflow_url": "https://api.github.com/repos/apache/superset/actions/workflows/3465823",
  "head_commit": {
    "id": "6d5949d4840893c47f8c61bc6e71961221af051f",
    "tree_id": "90014bb4e07ff2a1215e9a06a72a194752771f6f",
    "message": "docs(databases): add Atgenomix SeqsLab as the supported database.",
    "timestamp": "2023-09-04T15:21:17Z",
    "author": {
      "name": "apple",
      "email": "allen.chang@atgenomix.com"
    },
    "committer": {
      "name": "apple",
      "email": "allen.chang@atgenomix.com"
    }
  }
}
