{
  "id": 7802634974,
  "name": "Docker",
  "node_id": "WFR_kwLOAlosUs8AAAAB0RLC3g",
  "head_branch": "master",
  "head_sha": "7d79c7020d53ae7d0ebfb4071d13a446e50a2430",
  "path": ".github/workflows/docker.yml",
  "display_title": "fix(helm): Include option to use Redis with SSL",
  "run_number": 39908,
  "event": "pull_request",
  "status": "completed",
  "conclusion": "action_required",
  "workflow_id": 3465823,
  "check_suite_id": 20498164173,
  "check_suite_node_id": "CS_kwDOAlosUs8AAAAExckpzQ",
  "url": "https://api.github.com/repos/apache/superset/actions/runs/7802634974",
  "created_at": "2024-02-06T16:08:40Z",
  "updated_at": "2024-02-06T16:08:40Z",
  "actor": {
    "login": "shakeelansari63",
    "id": 8319053,
    "node_id": "MDQ6VXNlcjgzMTkwNTM=",
    "avatar_url": "https://avatars.githubusercontent.com/u/8319053?v=4",
    "gravatar_id": "",
    "url": "https://api.github.com/users/shakeelansari63",
    "html_url": "https://github.com/shakeelansari63",
    "followers_url": "https://api.github.com/users/shakeelansari63/followers",
    "following_url": "https://api.github.com/users/shakeelansari63/following{/other_user}",
    "gists_url": "https://api.github.com/users/shakeelansari63/gists{/gist_id}",
    "starred_url": "https://api.github.com/users/shakeelansari63/starred{/owner}{/repo}",
    "subscriptions_url": "https://api.github.com/users/shakeelansari63/subscriptions",
    "organizations_url": "https://api.github.com/users/shakeelansari63/orgs",
    "repos_url": "https://api.github.com/users/shakeelansari63/repos",
    "events_url": "https://api.github.com/users/shakeelansari63/events{/privacy}",
    "received_events_url": "https://api.github.com/users/shakeelansari63/received_events",
    "type": "User",
    "site_admin": false
  },
  "run_attempt": 1,
  "referenced_workflows": [],
  "run_started_at": "2024-02-06T16:08:40Z",
  "triggering_actor": {
    "login": "shakeelansari63",
    "id": 8319053,
    "node_id": "MDQ6VXNlcjgzMTkwNTM=",
    "avatar_url": "https://avatars.githubusercontent.com/u/8319053?v=4",
    "gravatar_id": "",
    "url": "https://api.github.com/users/shakeelansari63",
    "html_url": "https://github.com/shakeelansari63",
    "followers_url": "https://api.github.com/users/shakeelansari63/followers",
    "following_url": "https://api.github.com/users/shakeelansari63/following{/other_user}",
    "gists_url": "https://api.github.com/users/shakeelansari63/gists{/gist_id}",
    "starred_url": "https://api.github.com/users/shakeelansari63/starred{/owner}{/repo}",
    "subscriptions_url": "https://api.github.com/users/shakeelansari63/subscriptions",
    "organizations_url": "https://api.github.com/users/shakeelansari63/orgs",
    "repos_url": "https://api.github.com/users/shakeelansari63/repos",
    "events_url": "https://api.github.com/users/shakeelansari63/events{/privacy}",
    "received_events_url": "https://api.github.com/users/shakeelansari63/received_events",
    "type": "User",
    "site_admin": false
  },
  "jobs_url": "https://api.github.com/repos/apache/superset/actions/runs/7802634974/jobs",
  "logs_url": "https://api.github.com/repos/apache/superset/actions/runs/7802634974/logs",
  "check_suite_url": "https://api.github.com/repos/apache/superset/check-suites/20498164173",
  "artifacts_url": "https://api.github.com/repos/apache/superset/actions/runs/7802634974/artifacts",
  "cancel_url": "https://api.github.com/repos/apache/superset/actions/runs/7802634974/cancel",
  "rerun_url": "https://api.github.com/repos/apache/superset/actions/runs/7802634974/rerun",
  "previous_attempt_url": null,
  "workflow_url": "https://api.github.com/repos/apache/superset/actions/workflows/3465823",
  "head_commit": {
    "id": "7d79c7020d53ae7d0ebfb4071d13a446e50a2430",
    "tree_id": "ee03de2d1303de2ad2f1ecdd82b62dbe8dc537c3",
    "message": "Add Redis User",
    "timestamp": "2024-02-06T16:07:48Z",
    "author": {
      "name": "Shakeel Ansari",
      "email": "ShakeelAnsari63@Gmail.com"
    },
    "committer": {
      "name": "Shakeel Ansari",
      "email": "ShakeelAnsari63@Gmail.com"
    }
  }
}
