{
  "id": 1706949253,
  "name": "Docker",
  "node_id": "WFR_kwLOAlosUs5lvfqF",
  "head_branch": "master",
  "head_sha": "8dea7f500bea194f55c15c9f1511a35b2c328cd6",
  "run_number": 16524,
  "event": "push",
  "status": "completed",
  "conclusion": "success",
  "workflow_id": 3465823,
  "check_suite_id": 4958606477,
  "check_suite_node_id": "CS_kwDOAlosUs8AAAABJ45UjQ",
  "url": "https://api.github.com/repos/apache/superset/actions/runs/1706949253",
  "created_at": "2022-01-17T08:23:40Z",
  "updated_at": "2022-01-17T08:57:28Z",
  "run_attempt": 1,
  "run_started_at": "2022-01-17T08:23:40Z",
  "jobs_url": "https://api.github.com/repos/apache/superset/actions/runs/1706949253/jobs",
  "logs_url": "https://api.github.com/repos/apache/superset/actions/runs/1706949253/logs",
  "check_suite_url": "https://api.github.com/repos/apache/superset/check-suites/4958606477",
  "artifacts_url": "https://api.github.com/repos/apache/superset/actions/runs/1706949253/artifacts",
  "cancel_url": "https://api.github.com/repos/apache/superset/actions/runs/1706949253/cancel",
  "rerun_url": "https://api.github.com/repos/apache/superset/actions/runs/1706949253/rerun",
  "previous_attempt_url": null,
  "workflow_url": "https://api.github.com/repos/apache/superset/actions/workflows/3465823",
  "head_commit": {
    "id": "8dea7f500bea194f55c15c9f1511a35b2c328cd6",
    "tree_id": "54bdd974009b43d4dc9ed61fe23dd9791aa0c26e",
    "message": "fix(generator): more cleanup to plugin framework (#18027)\n\n* fix(generator): more cleanup to plugin framework\r\n\r\n* fix typo and package name\r\n\r\n* add docs\r\n\r\n* fix typo\r\n\r\n* Update superset-frontend/webpack.config.js\r\n\r\nCo-authored-by: Kamil Gabryjelski <kamil.gabryjelski@gmail.com>\r\n\r\n* fix generator reference\r\n\r\n* add steps to tutorial and fix package version\r\n\r\n* refine docs/readme\r\n\r\nCo-authored-by: Kamil Gabryjelski <kamil.gabryjelski@gmail.com>",
    "timestamp": "2022-01-17T08:23:35Z",
    "author": {
      "name": "Ville Brofeldt",
      "email": "33317356+villebro@users.noreply.github.com"
    },
    "committer": {
      "name": "GitHub",
      "email": "noreply@github.com"
    }
  }
}
