{
  "id": 6284291760,
  "name": "Docker",
  "node_id": "WFR_kwLOAlosUs8AAAABdpKusA",
  "head_branch": "master",
  "head_sha": "7c52b91b44a4fbd42353daab9bfceb1bcdd2cdb8",
  "path": ".github/workflows/docker.yml",
  "display_title": "feat(docker): Add ARM builds",
  "run_number": 35834,
  "event": "pull_request",
  "status": "completed",
  "conclusion": "failure",
  "workflow_id": 3465823,
  "check_suite_id": 16484743196,
  "check_suite_node_id": "CS_kwDOAlosUs8AAAAD1pE4HA",
  "url": "https://api.github.com/repos/apache/superset/actions/runs/6284291760",
  "created_at": "2023-09-23T14:30:40Z",
  "updated_at": "2023-09-23T15:13:26Z",
  "actor": {
    "login": "alekseyolg",
    "id": 86011874,
    "node_id": "MDQ6VXNlcjg2MDExODc0",
    "avatar_url": "https://avatars.githubusercontent.com/u/86011874?v=4",
    "gravatar_id": "",
    "url": "https://api.github.com/users/alekseyolg",
    "html_url": "https://github.com/alekseyolg",
    "followers_url": "https://api.github.com/users/alekseyolg/followers",
    "following_url": "https://api.github.com/users/alekseyolg/following{/other_user}",
    "gists_url": "https://api.github.com/users/alekseyolg/gists{/gist_id}",
    "starred_url": "https://api.github.com/users/alekseyolg/starred{/owner}{/repo}",
    "subscriptions_url": "https://api.github.com/users/alekseyolg/subscriptions",
    "organizations_url": "https://api.github.com/users/alekseyolg/orgs",
    "repos_url": "https://api.github.com/users/alekseyolg/repos",
    "events_url": "https://api.github.com/users/alekseyolg/events{/privacy}",
    "received_events_url": "https://api.github.com/users/alekseyolg/received_events",
    "type": "User",
    "site_admin": false
  },
  "run_attempt": 1,
  "referenced_workflows": [],
  "run_started_at": "2023-09-23T14:30:40Z",
  "triggering_actor": {
    "login": "alekseyolg",
    "id": 86011874,
    "node_id": "MDQ6VXNlcjg2MDExODc0",
    "avatar_url": "https://avatars.githubusercontent.com/u/86011874?v=4",
    "gravatar_id": "",
    "url": "https://api.github.com/users/alekseyolg",
    "html_url": "https://github.com/alekseyolg",
    "followers_url": "https://api.github.com/users/alekseyolg/followers",
    "following_url": "https://api.github.com/users/alekseyolg/following{/other_user}",
    "gists_url": "https://api.github.com/users/alekseyolg/gists{/gist_id}",
    "starred_url": "https://api.github.com/users/alekseyolg/starred{/owner}{/repo}",
    "subscriptions_url": "https://api.github.com/users/alekseyolg/subscriptions",
    "organizations_url": "https://api.github.com/users/alekseyolg/orgs",
    "repos_url": "https://api.github.com/users/alekseyolg/repos",
    "events_url": "https://api.github.com/users/alekseyolg/events{/privacy}",
    "received_events_url": "https://api.github.com/users/alekseyolg/received_events",
    "type": "User",
    "site_admin": false
  },
  "jobs_url": "https://api.github.com/repos/apache/superset/actions/runs/6284291760/jobs",
  "logs_url": "https://api.github.com/repos/apache/superset/actions/runs/6284291760/logs",
  "check_suite_url": "https://api.github.com/repos/apache/superset/check-suites/16484743196",
  "artifacts_url": "https://api.github.com/repos/apache/superset/actions/runs/6284291760/artifacts",
  "cancel_url": "https://api.github.com/repos/apache/superset/actions/runs/6284291760/cancel",
  "rerun_url": "https://api.github.com/repos/apache/superset/actions/runs/6284291760/rerun",
  "previous_attempt_url": null,
  "workflow_url": "https://api.github.com/repos/apache/superset/actions/workflows/3465823",
  "head_commit": {
    "id": "7c52b91b44a4fbd42353daab9bfceb1bcdd2cdb8",
    "tree_id": "c5a35b0b274a4c1bc2df4bd9f3128dc9152d57f5",
    "message": "change dockerfile",
    "timestamp": "2023-09-23T14:28:34Z",
    "author": {
      "name": "Aleksey Karpov",
      "email": "86011874+alekseyolg@users.noreply.github.com"
    },
    "committer": {
      "name": "Aleksey Karpov",
      "email": "86011874+alekseyolg@users.noreply.github.com"
    }
  }
}
