{
  "id": 3840598223,
  "name": "Docker",
  "node_id": "WFR_kwLOAlosUs7k6uDP",
  "head_branch": "master",
  "head_sha": "544c0eb963c2e3ac13503298f1bd9456a84bc6d2",
  "path": ".github/workflows/docker.yml",
  "display_title": "feat(chart): Added Papua New Guinea to countries map",
  "run_number": 28362,
  "event": "pull_request",
  "status": "completed",
  "conclusion": "action_required",
  "workflow_id": 3465823,
  "check_suite_id": 10184412402,
  "check_suite_node_id": "CS_kwDOAlosUs8AAAACXwnM8g",
  "url": "https://api.github.com/repos/apache/superset/actions/runs/3840598223",
  "created_at": "2023-01-04T18:27:45Z",
  "updated_at": "2023-01-04T18:27:45Z",
  "actor": {
    "login": "wilfred-wulbou",
    "id": 25276623,
    "node_id": "MDQ6VXNlcjI1Mjc2NjIz",
    "avatar_url": "https://avatars.githubusercontent.com/u/25276623?v=4",
    "gravatar_id": "",
    "url": "https://api.github.com/users/wilfred-wulbou",
    "html_url": "https://github.com/wilfred-wulbou",
    "followers_url": "https://api.github.com/users/wilfred-wulbou/followers",
    "following_url": "https://api.github.com/users/wilfred-wulbou/following{/other_user}",
    "gists_url": "https://api.github.com/users/wilfred-wulbou/gists{/gist_id}",
    "starred_url": "https://api.github.com/users/wilfred-wulbou/starred{/owner}{/repo}",
    "subscriptions_url": "https://api.github.com/users/wilfred-wulbou/subscriptions",
    "organizations_url": "https://api.github.com/users/wilfred-wulbou/orgs",
    "repos_url": "https://api.github.com/users/wilfred-wulbou/repos",
    "events_url": "https://api.github.com/users/wilfred-wulbou/events{/privacy}",
    "received_events_url": "https://api.github.com/users/wilfred-wulbou/received_events",
    "type": "User",
    "site_admin": false
  },
  "run_attempt": 1,
  "referenced_workflows": [],
  "run_started_at": "2023-01-04T18:27:45Z",
  "triggering_actor": {
    "login": "wilfred-wulbou",
    "id": 25276623,
    "node_id": "MDQ6VXNlcjI1Mjc2NjIz",
    "avatar_url": "https://avatars.githubusercontent.com/u/25276623?v=4",
    "gravatar_id": "",
    "url": "https://api.github.com/users/wilfred-wulbou",
    "html_url": "https://github.com/wilfred-wulbou",
    "followers_url": "https://api.github.com/users/wilfred-wulbou/followers",
    "following_url": "https://api.github.com/users/wilfred-wulbou/following{/other_user}",
    "gists_url": "https://api.github.com/users/wilfred-wulbou/gists{/gist_id}",
    "starred_url": "https://api.github.com/users/wilfred-wulbou/starred{/owner}{/repo}",
    "subscriptions_url": "https://api.github.com/users/wilfred-wulbou/subscriptions",
    "organizations_url": "https://api.github.com/users/wilfred-wulbou/orgs",
    "repos_url": "https://api.github.com/users/wilfred-wulbou/repos",
    "events_url": "https://api.github.com/users/wilfred-wulbou/events{/privacy}",
    "received_events_url": "https://api.github.com/users/wilfred-wulbou/received_events",
    "type": "User",
    "site_admin": false
  },
  "jobs_url": "https://api.github.com/repos/apache/superset/actions/runs/3840598223/jobs",
  "logs_url": "https://api.github.com/repos/apache/superset/actions/runs/3840598223/logs",
  "check_suite_url": "https://api.github.com/repos/apache/superset/check-suites/10184412402",
  "artifacts_url": "https://api.github.com/repos/apache/superset/actions/runs/3840598223/artifacts",
  "cancel_url": "https://api.github.com/repos/apache/superset/actions/runs/3840598223/cancel",
  "rerun_url": "https://api.github.com/repos/apache/superset/actions/runs/3840598223/rerun",
  "previous_attempt_url": null,
  "workflow_url": "https://api.github.com/repos/apache/superset/actions/workflows/3465823",
  "head_commit": {
    "id": "544c0eb963c2e3ac13503298f1bd9456a84bc6d2",
    "tree_id": "30ebff7d8655dda13b0e5c2f5901d6a770dac196",
    "message": "Merge branch 'apache:master' into master",
    "timestamp": "2023-01-04T17:54:26Z",
    "author": {
      "name": "wilfred-wulbou",
      "email": "wwulbou@gmail.com"
    },
    "committer": {
      "name": "GitHub",
      "email": "noreply@github.com"
    }
  }
}
