{
  "id": 1763716853,
  "name": "Docker",
  "node_id": "WFR_kwLOAlosUs5pIC71",
  "head_branch": "master",
  "head_sha": "c40b337978717b149984ed00c5359cf2c2394254",
  "run_number": 16947,
  "event": "push",
  "status": "completed",
  "conclusion": "success",
  "workflow_id": 3465823,
  "check_suite_id": 5102749306,
  "check_suite_node_id": "CS_kwDOAlosUs8AAAABMCXGeg",
  "url": "https://api.github.com/repos/apache/superset/actions/runs/1763716853",
  "created_at": "2022-01-28T21:29:50Z",
  "updated_at": "2022-01-28T21:48:04Z",
  "run_attempt": 1,
  "run_started_at": "2022-01-28T21:29:50Z",
  "jobs_url": "https://api.github.com/repos/apache/superset/actions/runs/1763716853/jobs",
  "logs_url": "https://api.github.com/repos/apache/superset/actions/runs/1763716853/logs",
  "check_suite_url": "https://api.github.com/repos/apache/superset/check-suites/5102749306",
  "artifacts_url": "https://api.github.com/repos/apache/superset/actions/runs/1763716853/artifacts",
  "cancel_url": "https://api.github.com/repos/apache/superset/actions/runs/1763716853/cancel",
  "rerun_url": "https://api.github.com/repos/apache/superset/actions/runs/1763716853/rerun",
  "previous_attempt_url": null,
  "workflow_url": "https://api.github.com/repos/apache/superset/actions/workflows/3465823",
  "head_commit": {
    "id": "c40b337978717b149984ed00c5359cf2c2394254",
    "tree_id": "b1a22bf99688aa0b1ead4a3d00cfe5862af633a8",
    "message": "feat: Added success toasts for database, dataset, chart, dashboard, and query imports (#18190)\n\n* Added imports toasts\r\n\r\n* Removed generic import toast\r\n\r\n* Remove addSuccessToast from props\r\n\r\n* Added addSuccessToast back to prop type\r\n\r\n* Made success toast strings translatable",
    "timestamp": "2022-01-28T21:29:44Z",
    "author": {
      "name": "Lyndsi Kay Williams",
      "email": "55605634+lyndsiWilliams@users.noreply.github.com"
    },
    "committer": {
      "name": "GitHub",
      "email": "noreply@github.com"
    }
  }
}
