{
  "id": 2263270807,
  "name": "Docker",
  "node_id": "WFR_kwLOAlosUs6G5sWX",
  "head_branch": "master",
  "head_sha": "7966d4747b5d917347eca315a618d33684d2fc8f",
  "run_number": 20617,
  "event": "pull_request",
  "status": "completed",
  "conclusion": "action_required",
  "workflow_id": 3465823,
  "check_suite_id": 6355214359,
  "check_suite_node_id": "CS_kwDOAlosUs8AAAABeszgFw",
  "url": "https://api.github.com/repos/apache/superset/actions/runs/2263270807",
  "created_at": "2022-05-03T10:27:12Z",
  "updated_at": "2022-05-03T10:27:12Z",
  "actor": {
    "login": "yeachan153",
    "id": 30076090,
    "node_id": "MDQ6VXNlcjMwMDc2MDkw",
    "avatar_url": "https://avatars.githubusercontent.com/u/30076090?v=4",
    "gravatar_id": "",
    "url": "https://api.github.com/users/yeachan153",
    "html_url": "https://github.com/yeachan153",
    "followers_url": "https://api.github.com/users/yeachan153/followers",
    "following_url": "https://api.github.com/users/yeachan153/following{/other_user}",
    "gists_url": "https://api.github.com/users/yeachan153/gists{/gist_id}",
    "starred_url": "https://api.github.com/users/yeachan153/starred{/owner}{/repo}",
    "subscriptions_url": "https://api.github.com/users/yeachan153/subscriptions",
    "organizations_url": "https://api.github.com/users/yeachan153/orgs",
    "repos_url": "https://api.github.com/users/yeachan153/repos",
    "events_url": "https://api.github.com/users/yeachan153/events{/privacy}",
    "received_events_url": "https://api.github.com/users/yeachan153/received_events",
    "type": "User",
    "site_admin": false
  },
  "run_attempt": 1,
  "run_started_at": "2022-05-03T10:27:12Z",
  "triggering_actor": {
    "login": "yeachan153",
    "id": 30076090,
    "node_id": "MDQ6VXNlcjMwMDc2MDkw",
    "avatar_url": "https://avatars.githubusercontent.com/u/30076090?v=4",
    "gravatar_id": "",
    "url": "https://api.github.com/users/yeachan153",
    "html_url": "https://github.com/yeachan153",
    "followers_url": "https://api.github.com/users/yeachan153/followers",
    "following_url": "https://api.github.com/users/yeachan153/following{/other_user}",
    "gists_url": "https://api.github.com/users/yeachan153/gists{/gist_id}",
    "starred_url": "https://api.github.com/users/yeachan153/starred{/owner}{/repo}",
    "subscriptions_url": "https://api.github.com/users/yeachan153/subscriptions",
    "organizations_url": "https://api.github.com/users/yeachan153/orgs",
    "repos_url": "https://api.github.com/users/yeachan153/repos",
    "events_url": "https://api.github.com/users/yeachan153/events{/privacy}",
    "received_events_url": "https://api.github.com/users/yeachan153/received_events",
    "type": "User",
    "site_admin": false
  },
  "jobs_url": "https://api.github.com/repos/apache/superset/actions/runs/2263270807/jobs",
  "logs_url": "https://api.github.com/repos/apache/superset/actions/runs/2263270807/logs",
  "check_suite_url": "https://api.github.com/repos/apache/superset/check-suites/6355214359",
  "artifacts_url": "https://api.github.com/repos/apache/superset/actions/runs/2263270807/artifacts",
  "cancel_url": "https://api.github.com/repos/apache/superset/actions/runs/2263270807/cancel",
  "rerun_url": "https://api.github.com/repos/apache/superset/actions/runs/2263270807/rerun",
  "previous_attempt_url": null,
  "workflow_url": "https://api.github.com/repos/apache/superset/actions/workflows/3465823",
  "head_commit": {
    "id": "7966d4747b5d917347eca315a618d33684d2fc8f",
    "tree_id": "47d90a40e9d5f8e5799dd99f2721c97404c6055a",
    "message": "Lint changes and parameter variable rename",
    "timestamp": "2022-05-03T10:26:59Z",
    "author": {
      "name": "Yeachan Park",
      "email": "yeachan153@gmail.com"
    },
    "committer": {
      "name": "Yeachan Park",
      "email": "yeachan153@gmail.com"
    }
  }
}
