{
  "id": 11468246870,
  "name": "Build & publish docker images",
  "node_id": "WFR_kwLOAlosUs8AAAACq4-PVg",
  "head_branch": "master",
  "head_sha": "35aaeb66bf9d01a4e3f1cb7c9c92989b1503b25e",
  "path": ".github/workflows/docker.yml",
  "display_title": "fix: fixed Add Metrics to Tree Chart (#29158)",
  "run_number": 47607,
  "event": "pull_request",
  "status": "completed",
  "conclusion": "action_required",
  "workflow_id": 3465823,
  "check_suite_id": 29958304449,
  "check_suite_node_id": "CS_kwDOAlosUs8AAAAG-adywQ",
  "url": "https://api.github.com/repos/apache/superset/actions/runs/11468246870",
  "created_at": "2024-10-22T20:45:40Z",
  "updated_at": "2024-10-22T20:45:40Z",
  "actor": {
    "login": "SBIN2010",
    "id": 132096459,
    "node_id": "U_kgDOB9-hyw",
    "avatar_url": "https://avatars.githubusercontent.com/u/132096459?v=4",
    "gravatar_id": "",
    "url": "https://api.github.com/users/SBIN2010",
    "html_url": "https://github.com/SBIN2010",
    "followers_url": "https://api.github.com/users/SBIN2010/followers",
    "following_url": "https://api.github.com/users/SBIN2010/following{/other_user}",
    "gists_url": "https://api.github.com/users/SBIN2010/gists{/gist_id}",
    "starred_url": "https://api.github.com/users/SBIN2010/starred{/owner}{/repo}",
    "subscriptions_url": "https://api.github.com/users/SBIN2010/subscriptions",
    "organizations_url": "https://api.github.com/users/SBIN2010/orgs",
    "repos_url": "https://api.github.com/users/SBIN2010/repos",
    "events_url": "https://api.github.com/users/SBIN2010/events{/privacy}",
    "received_events_url": "https://api.github.com/users/SBIN2010/received_events",
    "type": "User",
    "user_view_type": "public",
    "site_admin": false
  },
  "run_attempt": 1,
  "referenced_workflows": [],
  "run_started_at": "2024-10-22T20:45:40Z",
  "triggering_actor": {
    "login": "SBIN2010",
    "id": 132096459,
    "node_id": "U_kgDOB9-hyw",
    "avatar_url": "https://avatars.githubusercontent.com/u/132096459?v=4",
    "gravatar_id": "",
    "url": "https://api.github.com/users/SBIN2010",
    "html_url": "https://github.com/SBIN2010",
    "followers_url": "https://api.github.com/users/SBIN2010/followers",
    "following_url": "https://api.github.com/users/SBIN2010/following{/other_user}",
    "gists_url": "https://api.github.com/users/SBIN2010/gists{/gist_id}",
    "starred_url": "https://api.github.com/users/SBIN2010/starred{/owner}{/repo}",
    "subscriptions_url": "https://api.github.com/users/SBIN2010/subscriptions",
    "organizations_url": "https://api.github.com/users/SBIN2010/orgs",
    "repos_url": "https://api.github.com/users/SBIN2010/repos",
    "events_url": "https://api.github.com/users/SBIN2010/events{/privacy}",
    "received_events_url": "https://api.github.com/users/SBIN2010/received_events",
    "type": "User",
    "user_view_type": "public",
    "site_admin": false
  },
  "jobs_url": "https://api.github.com/repos/apache/superset/actions/runs/11468246870/jobs",
  "logs_url": "https://api.github.com/repos/apache/superset/actions/runs/11468246870/logs",
  "check_suite_url": "https://api.github.com/repos/apache/superset/check-suites/29958304449",
  "artifacts_url": "https://api.github.com/repos/apache/superset/actions/runs/11468246870/artifacts",
  "cancel_url": "https://api.github.com/repos/apache/superset/actions/runs/11468246870/cancel",
  "rerun_url": "https://api.github.com/repos/apache/superset/actions/runs/11468246870/rerun",
  "previous_attempt_url": null,
  "workflow_url": "https://api.github.com/repos/apache/superset/actions/workflows/3465823",
  "head_commit": {
    "id": "35aaeb66bf9d01a4e3f1cb7c9c92989b1503b25e",
    "tree_id": "68794887e019ba23e2f96ab3cd25305cb6dbff14",
    "message": "fix: clear modal after CSS templates is added",
    "timestamp": "2024-10-22T20:45:27Z",
    "author": {
      "name": "SBIN2010",
      "email": "Sbin2010@mail.ru"
    },
    "committer": {
      "name": "SBIN2010",
      "email": "Sbin2010@mail.ru"
    }
  }
}
