{
  "id": 5716942777,
  "name": "Docker",
  "node_id": "WFR_kwLOAlosUs8AAAABVMGfuQ",
  "head_branch": "master",
  "head_sha": "5f103072b0f006862c61abc0ab336b6a388ec95a",
  "path": ".github/workflows/docker.yml",
  "display_title": "fix: Python3.11 (str, Enum) issue (#24803)",
  "run_number": 34604,
  "event": "push",
  "status": "completed",
  "conclusion": "success",
  "workflow_id": 3465823,
  "check_suite_id": 14701292413,
  "check_suite_node_id": "CS_kwDOAlosUs8AAAADbEPrfQ",
  "url": "https://api.github.com/repos/apache/superset/actions/runs/5716942777",
  "created_at": "2023-07-31T16:04:14Z",
  "updated_at": "2023-07-31T16:19:26Z",
  "actor": {
    "login": "john-bodley",
    "id": 4567245,
    "node_id": "MDQ6VXNlcjQ1NjcyNDU=",
    "avatar_url": "https://avatars.githubusercontent.com/u/4567245?v=4",
    "gravatar_id": "",
    "url": "https://api.github.com/users/john-bodley",
    "html_url": "https://github.com/john-bodley",
    "followers_url": "https://api.github.com/users/john-bodley/followers",
    "following_url": "https://api.github.com/users/john-bodley/following{/other_user}",
    "gists_url": "https://api.github.com/users/john-bodley/gists{/gist_id}",
    "starred_url": "https://api.github.com/users/john-bodley/starred{/owner}{/repo}",
    "subscriptions_url": "https://api.github.com/users/john-bodley/subscriptions",
    "organizations_url": "https://api.github.com/users/john-bodley/orgs",
    "repos_url": "https://api.github.com/users/john-bodley/repos",
    "events_url": "https://api.github.com/users/john-bodley/events{/privacy}",
    "received_events_url": "https://api.github.com/users/john-bodley/received_events",
    "type": "User",
    "site_admin": false
  },
  "run_attempt": 1,
  "referenced_workflows": [],
  "run_started_at": "2023-07-31T16:04:14Z",
  "triggering_actor": {
    "login": "john-bodley",
    "id": 4567245,
    "node_id": "MDQ6VXNlcjQ1NjcyNDU=",
    "avatar_url": "https://avatars.githubusercontent.com/u/4567245?v=4",
    "gravatar_id": "",
    "url": "https://api.github.com/users/john-bodley",
    "html_url": "https://github.com/john-bodley",
    "followers_url": "https://api.github.com/users/john-bodley/followers",
    "following_url": "https://api.github.com/users/john-bodley/following{/other_user}",
    "gists_url": "https://api.github.com/users/john-bodley/gists{/gist_id}",
    "starred_url": "https://api.github.com/users/john-bodley/starred{/owner}{/repo}",
    "subscriptions_url": "https://api.github.com/users/john-bodley/subscriptions",
    "organizations_url": "https://api.github.com/users/john-bodley/orgs",
    "repos_url": "https://api.github.com/users/john-bodley/repos",
    "events_url": "https://api.github.com/users/john-bodley/events{/privacy}",
    "received_events_url": "https://api.github.com/users/john-bodley/received_events",
    "type": "User",
    "site_admin": false
  },
  "jobs_url": "https://api.github.com/repos/apache/superset/actions/runs/5716942777/jobs",
  "logs_url": "https://api.github.com/repos/apache/superset/actions/runs/5716942777/logs",
  "check_suite_url": "https://api.github.com/repos/apache/superset/check-suites/14701292413",
  "artifacts_url": "https://api.github.com/repos/apache/superset/actions/runs/5716942777/artifacts",
  "cancel_url": "https://api.github.com/repos/apache/superset/actions/runs/5716942777/cancel",
  "rerun_url": "https://api.github.com/repos/apache/superset/actions/runs/5716942777/rerun",
  "previous_attempt_url": null,
  "workflow_url": "https://api.github.com/repos/apache/superset/actions/workflows/3465823",
  "head_commit": {
    "id": "5f103072b0f006862c61abc0ab336b6a388ec95a",
    "tree_id": "8fa9953f1e62b4ed17c2446e7d8f42c32cdfd123",
    "message": "fix: Python3.11 (str, Enum) issue (#24803)",
    "timestamp": "2023-07-31T16:04:09Z",
    "author": {
      "name": "EugeneTorap",
      "email": "evgenykrutpro@gmail.com"
    },
    "committer": {
      "name": "GitHub",
      "email": "noreply@github.com"
    }
  }
}
