{
  "id": 4471757668,
  "name": "Docker",
  "node_id": "WFR_kwLOAlosUs8AAAABCombZA",
  "head_branch": "master",
  "head_sha": "ffc0a81e852d4de285f092537d7affd9628dd1a6",
  "path": ".github/workflows/docker.yml",
  "display_title": "chore(native-filters): Fetch only the required dataset fields (#23303)",
  "run_number": 30630,
  "event": "push",
  "status": "completed",
  "conclusion": "success",
  "workflow_id": 3465823,
  "check_suite_id": 11686233494,
  "check_suite_node_id": "CS_kwDOAlosUs8AAAACuI3Flg",
  "url": "https://api.github.com/repos/apache/superset/actions/runs/4471757668",
  "created_at": "2023-03-20T18:43:45Z",
  "updated_at": "2023-03-20T19:01:17Z",
  "actor": {
    "login": "john-bodley",
    "id": 4567245,
    "node_id": "MDQ6VXNlcjQ1NjcyNDU=",
    "avatar_url": "https://avatars.githubusercontent.com/u/4567245?v=4",
    "gravatar_id": "",
    "url": "https://api.github.com/users/john-bodley",
    "html_url": "https://github.com/john-bodley",
    "followers_url": "https://api.github.com/users/john-bodley/followers",
    "following_url": "https://api.github.com/users/john-bodley/following{/other_user}",
    "gists_url": "https://api.github.com/users/john-bodley/gists{/gist_id}",
    "starred_url": "https://api.github.com/users/john-bodley/starred{/owner}{/repo}",
    "subscriptions_url": "https://api.github.com/users/john-bodley/subscriptions",
    "organizations_url": "https://api.github.com/users/john-bodley/orgs",
    "repos_url": "https://api.github.com/users/john-bodley/repos",
    "events_url": "https://api.github.com/users/john-bodley/events{/privacy}",
    "received_events_url": "https://api.github.com/users/john-bodley/received_events",
    "type": "User",
    "site_admin": false
  },
  "run_attempt": 1,
  "referenced_workflows": [],
  "run_started_at": "2023-03-20T18:43:45Z",
  "triggering_actor": {
    "login": "john-bodley",
    "id": 4567245,
    "node_id": "MDQ6VXNlcjQ1NjcyNDU=",
    "avatar_url": "https://avatars.githubusercontent.com/u/4567245?v=4",
    "gravatar_id": "",
    "url": "https://api.github.com/users/john-bodley",
    "html_url": "https://github.com/john-bodley",
    "followers_url": "https://api.github.com/users/john-bodley/followers",
    "following_url": "https://api.github.com/users/john-bodley/following{/other_user}",
    "gists_url": "https://api.github.com/users/john-bodley/gists{/gist_id}",
    "starred_url": "https://api.github.com/users/john-bodley/starred{/owner}{/repo}",
    "subscriptions_url": "https://api.github.com/users/john-bodley/subscriptions",
    "organizations_url": "https://api.github.com/users/john-bodley/orgs",
    "repos_url": "https://api.github.com/users/john-bodley/repos",
    "events_url": "https://api.github.com/users/john-bodley/events{/privacy}",
    "received_events_url": "https://api.github.com/users/john-bodley/received_events",
    "type": "User",
    "site_admin": false
  },
  "jobs_url": "https://api.github.com/repos/apache/superset/actions/runs/4471757668/jobs",
  "logs_url": "https://api.github.com/repos/apache/superset/actions/runs/4471757668/logs",
  "check_suite_url": "https://api.github.com/repos/apache/superset/check-suites/11686233494",
  "artifacts_url": "https://api.github.com/repos/apache/superset/actions/runs/4471757668/artifacts",
  "cancel_url": "https://api.github.com/repos/apache/superset/actions/runs/4471757668/cancel",
  "rerun_url": "https://api.github.com/repos/apache/superset/actions/runs/4471757668/rerun",
  "previous_attempt_url": null,
  "workflow_url": "https://api.github.com/repos/apache/superset/actions/workflows/3465823",
  "head_commit": {
    "id": "ffc0a81e852d4de285f092537d7affd9628dd1a6",
    "tree_id": "736a3e271bc1dec53e199377e96d9017f1bd7bc4",
    "message": "chore(native-filters): Fetch only the required dataset fields (#23303)\n\nCo-authored-by: Michael S. Molina <70410625+michael-s-molina@users.noreply.github.com>",
    "timestamp": "2023-03-20T18:43:39Z",
    "author": {
      "name": "John Bodley",
      "email": "4567245+john-bodley@users.noreply.github.com"
    },
    "committer": {
      "name": "GitHub",
      "email": "noreply@github.com"
    }
  }
}
