{
  "id": 12404617531,
  "name": "Build & publish docker images",
  "node_id": "WFR_kwLOAlosUs8AAAAC419xOw",
  "head_branch": "master",
  "head_sha": "e51b95ffa8377470ee5495a37ff5ec03b4de1aff",
  "path": ".github/workflows/docker.yml",
  "display_title": "chore: enforce more ruff rules (#31447)",
  "run_number": 49267,
  "event": "push",
  "status": "completed",
  "conclusion": "success",
  "workflow_id": 3465823,
  "check_suite_id": 32242622081,
  "check_suite_node_id": "CS_kwDOAlosUs8AAAAHgc9egQ",
  "url": "https://api.github.com/repos/apache/superset/actions/runs/12404617531",
  "created_at": "2024-12-19T01:41:37Z",
  "updated_at": "2024-12-19T02:00:33Z",
  "actor": {
    "login": "mistercrunch",
    "id": 487433,
    "node_id": "MDQ6VXNlcjQ4NzQzMw==",
    "avatar_url": "https://avatars.githubusercontent.com/u/487433?v=4",
    "gravatar_id": "",
    "url": "https://api.github.com/users/mistercrunch",
    "html_url": "https://github.com/mistercrunch",
    "followers_url": "https://api.github.com/users/mistercrunch/followers",
    "following_url": "https://api.github.com/users/mistercrunch/following{/other_user}",
    "gists_url": "https://api.github.com/users/mistercrunch/gists{/gist_id}",
    "starred_url": "https://api.github.com/users/mistercrunch/starred{/owner}{/repo}",
    "subscriptions_url": "https://api.github.com/users/mistercrunch/subscriptions",
    "organizations_url": "https://api.github.com/users/mistercrunch/orgs",
    "repos_url": "https://api.github.com/users/mistercrunch/repos",
    "events_url": "https://api.github.com/users/mistercrunch/events{/privacy}",
    "received_events_url": "https://api.github.com/users/mistercrunch/received_events",
    "type": "User",
    "user_view_type": "public",
    "site_admin": false
  },
  "run_attempt": 1,
  "referenced_workflows": [],
  "run_started_at": "2024-12-19T01:41:37Z",
  "triggering_actor": {
    "login": "mistercrunch",
    "id": 487433,
    "node_id": "MDQ6VXNlcjQ4NzQzMw==",
    "avatar_url": "https://avatars.githubusercontent.com/u/487433?v=4",
    "gravatar_id": "",
    "url": "https://api.github.com/users/mistercrunch",
    "html_url": "https://github.com/mistercrunch",
    "followers_url": "https://api.github.com/users/mistercrunch/followers",
    "following_url": "https://api.github.com/users/mistercrunch/following{/other_user}",
    "gists_url": "https://api.github.com/users/mistercrunch/gists{/gist_id}",
    "starred_url": "https://api.github.com/users/mistercrunch/starred{/owner}{/repo}",
    "subscriptions_url": "https://api.github.com/users/mistercrunch/subscriptions",
    "organizations_url": "https://api.github.com/users/mistercrunch/orgs",
    "repos_url": "https://api.github.com/users/mistercrunch/repos",
    "events_url": "https://api.github.com/users/mistercrunch/events{/privacy}",
    "received_events_url": "https://api.github.com/users/mistercrunch/received_events",
    "type": "User",
    "user_view_type": "public",
    "site_admin": false
  },
  "jobs_url": "https://api.github.com/repos/apache/superset/actions/runs/12404617531/jobs",
  "logs_url": "https://api.github.com/repos/apache/superset/actions/runs/12404617531/logs",
  "check_suite_url": "https://api.github.com/repos/apache/superset/check-suites/32242622081",
  "artifacts_url": "https://api.github.com/repos/apache/superset/actions/runs/12404617531/artifacts",
  "cancel_url": "https://api.github.com/repos/apache/superset/actions/runs/12404617531/cancel",
  "rerun_url": "https://api.github.com/repos/apache/superset/actions/runs/12404617531/rerun",
  "previous_attempt_url": null,
  "workflow_url": "https://api.github.com/repos/apache/superset/actions/workflows/3465823",
  "head_commit": {
    "id": "e51b95ffa8377470ee5495a37ff5ec03b4de1aff",
    "tree_id": "0426a1856403d52d1a9b93ab8167d75580eec545",
    "message": "chore: enforce more ruff rules (#31447)\n\nCo-authored-by: Elizabeth Thompson <eschutho@gmail.com>",
    "timestamp": "2024-12-19T01:41:34Z",
    "author": {
      "name": "Maxime Beauchemin",
      "email": "maximebeauchemin@gmail.com"
    },
    "committer": {
      "name": "GitHub",
      "email": "noreply@github.com"
    }
  }
}
