{
  "id": 1350306922,
  "name": "Docker",
  "node_id": "WFR_kwLOAlosUs5QfAxq",
  "head_branch": "master",
  "head_sha": "40b88f04f6d360d66fcab7206e2e481d71ddf884",
  "run_number": 13905,
  "event": "push",
  "status": "completed",
  "conclusion": "success",
  "workflow_id": 3465823,
  "check_suite_id": 4074338236,
  "check_suite_node_id": "CS_kwDOAlosUs7y2Xe8",
  "url": "https://api.github.com/repos/apache/superset/actions/runs/1350306922",
  "created_at": "2021-10-17T00:46:17Z",
  "updated_at": "2021-10-17T01:03:01Z",
  "run_attempt": 1,
  "run_started_at": "2021-10-17T00:46:17Z",
  "jobs_url": "https://api.github.com/repos/apache/superset/actions/runs/1350306922/jobs",
  "logs_url": "https://api.github.com/repos/apache/superset/actions/runs/1350306922/logs",
  "check_suite_url": "https://api.github.com/repos/apache/superset/check-suites/4074338236",
  "artifacts_url": "https://api.github.com/repos/apache/superset/actions/runs/1350306922/artifacts",
  "cancel_url": "https://api.github.com/repos/apache/superset/actions/runs/1350306922/cancel",
  "rerun_url": "https://api.github.com/repos/apache/superset/actions/runs/1350306922/rerun",
  "previous_attempt_url": null,
  "workflow_url": "https://api.github.com/repos/apache/superset/actions/workflows/3465823",
  "head_commit": {
    "id": "40b88f04f6d360d66fcab7206e2e481d71ddf884",
    "tree_id": "d0c9e8c4bd520ac17788b80f2fde0487b32b01d5",
    "message": "feat: DBC UI Snowflake Form (#16856)\n\n* update snowflake spec for dyanmic form\r\n\r\n* feat(snowflake): Snowflake dynamic form (#16861)\r\n\r\n* snowflake frontend\r\n\r\n* snowflake frontend\r\n\r\n* refactor(DB Connections): Build Snowflake Dynamic Form (#16875)\r\n\r\n* moved all non-BasicParameters into own field\r\n\r\n* refactored DB Connection Form made ValidatedInput\r\n\r\n* quick fix\r\n\r\n* fixed ValidatedInputField (#16934)\r\n\r\n* add logic to check for required fields (#17022)\r\n\r\n* fix\r\n\r\n* fix linting\r\n\r\n* remove host\r\n\r\n* Update EncryptedField.tsx\r\n\r\nCo-authored-by: AAfghahi <48933336+AAfghahi@users.noreply.github.com>",
    "timestamp": "2021-10-17T00:46:06Z",
    "author": {
      "name": "Hugh A. Miles II",
      "email": "hughmil3s@gmail.com"
    },
    "committer": {
      "name": "GitHub",
      "email": "noreply@github.com"
    }
  }
}
