{
  "id": 3971116873,
  "name": "Docker",
  "node_id": "WFR_kwLOAlosUs7ssm9J",
  "head_branch": "master",
  "head_sha": "a8b023c0358cfad0aa3f249d7a3164026f91e116",
  "path": ".github/workflows/docker.yml",
  "display_title": "wip: feat: Add Ocient support",
  "run_number": 28993,
  "event": "pull_request",
  "status": "completed",
  "conclusion": "action_required",
  "workflow_id": 3465823,
  "check_suite_id": 10496149260,
  "check_suite_node_id": "CS_kwDOAlosUs8AAAACcZ6HDA",
  "url": "https://api.github.com/repos/apache/superset/actions/runs/3971116873",
  "created_at": "2023-01-20T20:39:33Z",
  "updated_at": "2023-01-20T20:39:33Z",
  "actor": {
    "login": "alexclavel-ocient",
    "id": 111374753,
    "node_id": "U_kgDOBqNxoQ",
    "avatar_url": "https://avatars.githubusercontent.com/u/111374753?v=4",
    "gravatar_id": "",
    "url": "https://api.github.com/users/alexclavel-ocient",
    "html_url": "https://github.com/alexclavel-ocient",
    "followers_url": "https://api.github.com/users/alexclavel-ocient/followers",
    "following_url": "https://api.github.com/users/alexclavel-ocient/following{/other_user}",
    "gists_url": "https://api.github.com/users/alexclavel-ocient/gists{/gist_id}",
    "starred_url": "https://api.github.com/users/alexclavel-ocient/starred{/owner}{/repo}",
    "subscriptions_url": "https://api.github.com/users/alexclavel-ocient/subscriptions",
    "organizations_url": "https://api.github.com/users/alexclavel-ocient/orgs",
    "repos_url": "https://api.github.com/users/alexclavel-ocient/repos",
    "events_url": "https://api.github.com/users/alexclavel-ocient/events{/privacy}",
    "received_events_url": "https://api.github.com/users/alexclavel-ocient/received_events",
    "type": "User",
    "site_admin": false
  },
  "run_attempt": 1,
  "referenced_workflows": [],
  "run_started_at": "2023-01-20T20:39:33Z",
  "triggering_actor": {
    "login": "alexclavel-ocient",
    "id": 111374753,
    "node_id": "U_kgDOBqNxoQ",
    "avatar_url": "https://avatars.githubusercontent.com/u/111374753?v=4",
    "gravatar_id": "",
    "url": "https://api.github.com/users/alexclavel-ocient",
    "html_url": "https://github.com/alexclavel-ocient",
    "followers_url": "https://api.github.com/users/alexclavel-ocient/followers",
    "following_url": "https://api.github.com/users/alexclavel-ocient/following{/other_user}",
    "gists_url": "https://api.github.com/users/alexclavel-ocient/gists{/gist_id}",
    "starred_url": "https://api.github.com/users/alexclavel-ocient/starred{/owner}{/repo}",
    "subscriptions_url": "https://api.github.com/users/alexclavel-ocient/subscriptions",
    "organizations_url": "https://api.github.com/users/alexclavel-ocient/orgs",
    "repos_url": "https://api.github.com/users/alexclavel-ocient/repos",
    "events_url": "https://api.github.com/users/alexclavel-ocient/events{/privacy}",
    "received_events_url": "https://api.github.com/users/alexclavel-ocient/received_events",
    "type": "User",
    "site_admin": false
  },
  "jobs_url": "https://api.github.com/repos/apache/superset/actions/runs/3971116873/jobs",
  "logs_url": "https://api.github.com/repos/apache/superset/actions/runs/3971116873/logs",
  "check_suite_url": "https://api.github.com/repos/apache/superset/check-suites/10496149260",
  "artifacts_url": "https://api.github.com/repos/apache/superset/actions/runs/3971116873/artifacts",
  "cancel_url": "https://api.github.com/repos/apache/superset/actions/runs/3971116873/cancel",
  "rerun_url": "https://api.github.com/repos/apache/superset/actions/runs/3971116873/rerun",
  "previous_attempt_url": null,
  "workflow_url": "https://api.github.com/repos/apache/superset/actions/workflows/3465823",
  "head_commit": {
    "id": "a8b023c0358cfad0aa3f249d7a3164026f91e116",
    "tree_id": "be119e9be09f2061170dad782314b710953b2dd4",
    "message": "feat: add OcientEngineSpec",
    "timestamp": "2023-01-13T18:44:43Z",
    "author": {
      "name": "jwilliams-ocient",
      "email": "60358443+jwilliams-ocient@users.noreply.github.com"
    },
    "committer": {
      "name": "GitHub",
      "email": "noreply@github.com"
    }
  }
}
